deepextract/__init__.py
deepextract/deepextract.py
test/__init__.py
test/test_deepextract.py
deepextract-1.0.9.dist-info/LICENSE
deepextract-1.0.9.dist-info/METADATA
deepextract-1.0.9.dist-info/WHEEL
deepextract-1.0.9.dist-info/top_level.txt
deepextract-1.0.9.dist-info/RECORD
