Metadata-Version: 2.1
Name: deepextract
Version: 1.0.9
Summary: A Python library to parse JSON, YAML files and extract deeply nested keys.
Home-page: https://github.com/ya332/deepextract
Author: Yigit Alparslan
Author-email: alparslanyigitcan@gmail.com
License: MIT
Platform: UNKNOWN
Classifier: Development Status :: 2 - Pre-Alpha
Classifier: License :: OSI Approved :: MIT License
Classifier: Programming Language :: Python
Classifier: Programming Language :: Python :: 3
Classifier: Programming Language :: Python :: 3.6
Classifier: Programming Language :: Python :: 3.7
Classifier: Programming Language :: Python :: 3.8
Classifier: Programming Language :: Python :: 3.9
Requires-Python: >=3.6.0
